archivematica_omekas/__init__.py
archivematica_omekas/_modidx.py
archivematica_omekas/api.py
archivematica_omekas-0.0.1.dist-info/LICENSE
archivematica_omekas-0.0.1.dist-info/METADATA
archivematica_omekas-0.0.1.dist-info/WHEEL
archivematica_omekas-0.0.1.dist-info/entry_points.txt
archivematica_omekas-0.0.1.dist-info/top_level.txt
archivematica_omekas-0.0.1.dist-info/RECORD
