Metadata-Version: 2.1
Name: archivematica-omekas
Version: 0.0.1
Home-page: https://github.com/nakamura196/archivematica-omekas
Author: Satoru
Author-email: you@example.com
License: Apache Software License 2.0
Keywords: nbdev jupyter notebook python
Classifier: Development Status :: 4 - Beta
Classifier: Intended Audience :: Developers
Classifier: Natural Language :: English
Classifier: Programming Language :: Python :: 3.7
Classifier: Programming Language :: Python :: 3.8
Classifier: Programming Language :: Python :: 3.9
Classifier: Programming Language :: Python :: 3.10
Classifier: License :: OSI Approved :: Apache Software License
Requires-Python: >=3.7
License-File: LICENSE
Requires-Dist: fastcore
Requires-Dist: pandas
Requires-Dist: omeka-s-tools2
Requires-Dist: bs4
Requires-Dist: tqdm
Provides-Extra: dev
